etc/settings.py
kenkun/__init__.py
kenkun/__main__.py
kenkun/util/__init__.py
kenkun/util/fields.py
kenkun-0.1.10.dist-info/METADATA
kenkun-0.1.10.dist-info/WHEEL
kenkun-0.1.10.dist-info/entry_points.txt
kenkun-0.1.10.dist-info/top_level.txt
kenkun-0.1.10.dist-info/RECORD
