Metadata-Version: 2.4
Name: kenkun
Version: 0.1.10
Summary: A cli ui to generate projects in python.
Author-email: Sylvio Ximenez de Azevedo Neto <sylvioazevedo@gmail.com>
License: MIT License
Project-URL: Homepage, https://github.com/sylvioazevedo/kenkun
Keywords: cli,ui,project,generator,python
Classifier: Development Status :: 4 - Beta
Classifier: Intended Audience :: Developers
Classifier: Programming Language :: Python :: 3
Classifier: Programming Language :: Python :: 3.12
Classifier: Programming Language :: Python :: Implementation :: CPython
Classifier: Programming Language :: Python :: Implementation :: PyPy
Classifier: Topic :: Software Development :: Build Tools
Requires-Python: >=3.12
Requires-Dist: jinja2
